pydoku2/__init__.py
pydoku2/image.py
pydoku2/solver.py
pydoku2/sudoku-solver.py
pydoku2/trainer.py
pydoku2-0.1.0.dist-info/WHEEL
pydoku2-0.1.0.dist-info/METADATA
pydoku2-0.1.0.dist-info/RECORD
