Metadata-Version: 2.1
Name: pydoku2
Version: 0.1.0
Summary: 
Author: alexgQQ
Requires-Python: >=3.7,<4.0
Classifier: Programming Language :: Python :: 3
Classifier: Programming Language :: Python :: 3.7
Classifier: Programming Language :: Python :: 3.8
Classifier: Programming Language :: Python :: 3.9
Requires-Dist: Keras (>=2.4.3,<3.0.0)
Requires-Dist: click (>=7.1.2,<8.0.0)
Requires-Dist: numpy (>=1.19.5,<2.0.0)
Requires-Dist: opencv-python (>=4.5.1,<5.0.0)
Requires-Dist: tensorflow-cpu (>=2.4.1,<3.0.0)
